lusya/__init__.py
lusya/utils.py
lusya/base/__init__.py
lusya/base/backend.py
lusya/base/fields.py
lusya/base/mapping.py
lusya/base/parser.py
lusya/base/searchhelper.py
lusya/base/searchset.py
lusya/django/__init__.py
lusya/django/backend.py
lusya/django/fields.py
lusya/django/mapping.py
lusya/django/parser.py
lusya/django/searchhelper.py
lusya/django/searchset.py
lusya-0.2.0.dist-info/LICENSE
lusya-0.2.0.dist-info/METADATA
lusya-0.2.0.dist-info/WHEEL
lusya-0.2.0.dist-info/top_level.txt
lusya-0.2.0.dist-info/RECORD
